[
  {
    "_id": "update_by_date",
    "_type": "visualization",
    "_source": {
      "title": "update_by_date",
      "visState": "{\"title\":\"New Visualization\",\"type\":\"histogram\",\"params\":{\"shareYAxis\":true,\"addTooltip\":true,\"addLegend\":true,\"scale\":\"linear\",\"mode\":\"stacked\",\"times\":[],\"addTimeMarker\":false,\"defaultYExtents\":false,\"setYExtents\":false,\"yAxis\":{}},\"aggs\":[{\"id\":\"1\",\"type\":\"count\",\"schema\":\"metric\",\"params\":{}},{\"id\":\"2\",\"type\":\"date_histogram\",\"schema\":\"segment\",\"params\":{\"field\":\"updated\",\"interval\":\"auto\",\"customInterval\":\"2h\",\"min_doc_count\":1,\"extended_bounds\":{}}}],\"listeners\":{}}",
      "uiStateJSON": "{\"vis\":{\"legendOpen\":false},\"spy\":{\"mode\":{\"name\":null,\"fill\":false}}}",
      "description": "",
      "version": 1,
      "kibanaSavedObjectMeta": {
        "searchSourceJSON": "{\"index\":\"finess\",\"query\":{\"query_string\":{\"query\":\"*\",\"analyze_wildcard\":true}},\"filter\":[]}"
      }
    }
  },
  {
    "_id": "count_by_dept",
    "_type": "visualization",
    "_source": {
      "title": "count_by_dept",
      "visState": "{\"title\":\"New Visualization\",\"type\":\"pie\",\"params\":{\"shareYAxis\":true,\"addTooltip\":true,\"addLegend\":true,\"isDonut\":true},\"aggs\":[{\"id\":\"1\",\"type\":\"count\",\"schema\":\"metric\",\"params\":{}},{\"id\":\"2\",\"type\":\"terms\",\"schema\":\"segment\",\"params\":{\"field\":\"dept\",\"size\":100,\"order\":\"desc\",\"orderBy\":\"1\"}}],\"listeners\":{}}",
      "uiStateJSON": "{}",
      "description": "",
      "version": 1,
      "kibanaSavedObjectMeta": {
        "searchSourceJSON": "{\"index\":\"finess\",\"query\":{\"query_string\":{\"query\":\"*\",\"analyze_wildcard\":true}},\"filter\":[]}"
      }
    }
  },
  {
    "_id": "update_by_dept",
    "_type": "visualization",
    "_source": {
      "title": "update_by_dept",
      "visState": "{\"title\":\"New Visualization\",\"type\":\"pie\",\"params\":{\"shareYAxis\":true,\"addTooltip\":true,\"addLegend\":true,\"isDonut\":true},\"aggs\":[{\"id\":\"1\",\"type\":\"count\",\"schema\":\"metric\",\"params\":{}},{\"id\":\"2\",\"type\":\"terms\",\"schema\":\"segment\",\"params\":{\"field\":\"dept\",\"size\":100,\"order\":\"desc\",\"orderBy\":\"1\"}}],\"listeners\":{}}",
      "uiStateJSON": "{}",
      "description": "",
      "version": 1,
      "kibanaSavedObjectMeta": {
        "searchSourceJSON": "{\"index\":\"finess\",\"query\":{\"query_string\":{\"query\":\"*\",\"analyze_wildcard\":true}},\"filter\":[]}"
      }
    }
  },
  {
    "_id": "count_updated",
    "_type": "visualization",
    "_source": {
      "title": "count_updated",
      "visState": "{\"title\":\"count_updated\",\"type\":\"metric\",\"params\":{\"handleNoResults\":true,\"fontSize\":\"40\"},\"aggs\":[{\"id\":\"1\",\"type\":\"count\",\"schema\":\"metric\",\"params\":{}}],\"listeners\":{}}",
      "uiStateJSON": "{}",
      "description": "",
      "version": 1,
      "kibanaSavedObjectMeta": {
        "searchSourceJSON": "{\"index\":\"finess\",\"query\":{\"query_string\":{\"query\":\"*\",\"analyze_wildcard\":true}},\"filter\":[]}"
      }
    }
  }
]